csgo_demoparser-0.0.1.dist-info/DESCRIPTION.rst
csgo_demoparser-0.0.1.dist-info/METADATA
csgo_demoparser-0.0.1.dist-info/LICENSE.txt
csgo_demoparser-0.0.1.dist-info/top_level.txt
csgo_demoparser-0.0.1.dist-info/metadata.json
csgo_demoparser-0.0.1.dist-info/RECORD
csgo_demoparser-0.0.1.dist-info/WHEEL
csgo_demoparser-0.0.1.dist-info/pbr.json
demoparser/bitbuffer.pxd
demoparser/bytebuffer.py
demoparser/bitbuffer.pyx
demoparser/util.pxd
demoparser/demofile.c
demoparser/bitbuffer.cpython-35m-x86_64-linux-gnu.so
demoparser/util.cpython-35m-x86_64-linux-gnu.so
demoparser/props.cpython-35m-x86_64-linux-gnu.so
demoparser/structures.py
demoparser/consts.py
demoparser/_setup_hooks.py
demoparser/props.pyx
demoparser/util.c
demoparser/props.pxd
demoparser/fields.py
demoparser/bitbuffer.c
demoparser/__init__.py
demoparser/props.c
demoparser/util.pyx
demoparser/demofile.pyx
demoparser/demofile.cpython-35m-x86_64-linux-gnu.so
demoparser/protobufs/cstrike15_usermessages_pb2.py
demoparser/protobufs/steamdatagram_messages.proto
demoparser/protobufs/gcsdk_gcmessages_pb2.py
demoparser/protobufs/engine_gcmessages_pb2.py
demoparser/protobufs/gcsystemmsgs.proto
demoparser/protobufs/steammessages_pb2.py
demoparser/protobufs/gcsystemmsgs_pb2.py
demoparser/protobufs/base_gcmessages.proto
demoparser/protobufs/fatdemo.proto
demoparser/protobufs/cstrike15_usermessages.proto
demoparser/protobufs/fatdemo_pb2.py
demoparser/protobufs/steamdatagram_messages_pb2.py
demoparser/protobufs/steammessages.proto
demoparser/protobufs/netmessages_pb2.py
demoparser/protobufs/LICENSE
demoparser/protobufs/base_gcmessages_pb2.py
demoparser/protobufs/__init__.py
demoparser/protobufs/network_connection_pb2.py
demoparser/protobufs/econ_gcmessages_pb2.py
demoparser/protobufs/cstrike15_gcmessages_pb2.py
demoparser/protobufs/netmessages.proto
demoparser/protobufs/network_connection.proto
demoparser/protobufs/econ_gcmessages.proto
demoparser/protobufs/gcsdk_gcmessages.proto
demoparser/protobufs/cstrike15_gcmessages.proto
demoparser/protobufs/engine_gcmessages.proto
demoparser/entities/entity_list.py
demoparser/entities/weapon.py
demoparser/entities/player.py
demoparser/entities/base.py
demoparser/entities/team.py
demoparser/entities/__init__.py
demoparser/entities/game_rules.py
