Metadata-Version: 2.0
Name: csgo-demoparser
Version: 0.0.1
Summary: CS:GO demo file parser.
Home-page: https://github.com/ibm-dev-incubator/demoparser
Author: Ryan Moe
Author-email: ryan.moe@gmail.com
License: Apache-2
Keywords: setup
Requires-Dist: suitcase
Requires-Dist: cython
Requires-Dist: protobuf
Requires-Dist: sphinx
